hub/__init__.py
hub/antonyms/__init__.py
hub/antonyms/antonyms.py
hub/antonyms/antonyms_test.py
hub/gaokao_cloze_hint/__init__.py
hub/gaokao_cloze_hint/gaokao_cloze_hint.py
hub/gaokao_cloze_hint/gaokao_cloze_hint_test.py
hub/gaokao_cloze_multiple_choice/__init__.py
hub/gaokao_cloze_multiple_choice/gaokao_cloze_multiple_choice.py
hub/gaokao_cloze_multiple_choice/gaokao_cloze_multiple_choice_test.py
hub/gaokao_essay_writing/__init__.py
hub/gaokao_essay_writing/gaokao_essay_writing.py
hub/gaokao_essay_writing/gaokao_essay_writing_test.py
hub/gaokao_grammar_correction/__init__.py
hub/gaokao_grammar_correction/gaokao_grammar_correction.py
hub/gaokao_grammar_correction/gaokao_grammar_correction_test.py
hub/gaokao_listening/__init__.py
hub/gaokao_listening/gaokao_listening.py
hub/gaokao_listening/gaokao_listening_test.py
hub/gaokao_reading_comprehension/__init__.py
hub/gaokao_reading_comprehension/gaokao_reading_comprehension.py
hub/gaokao_reading_comprehension/gaokao_reading_comprehension_test.py
hub/linguistic_acceptability_classification/__init__.py
hub/linguistic_acceptability_classification/linguistic_acceptability_classification.py
hub/linguistic_acceptability_classification/linguistic_acceptability_classification_test.py
hub/machine_translation/__init__.py
hub/machine_translation/machine_translation.py
hub/machine_translation/machine_translation_test.py
hub/math_calculation/__init__.py
hub/math_calculation/math_calculation.py
hub/math_calculation/math_calculation_test.py
hub/natural_language_inference/__init__.py
hub/natural_language_inference/natural_language_inference.py
hub/natural_language_inference/natural_language_inference_test.py
hub/sentiment_classifier/__init__.py
hub/sentiment_classifier/sentiment_classifier.py
hub/sentiment_classifier/sentiment_classifier_test.py
softwares/__init__.py
softwares/config.py
softwares/info.py
softwares/licenses.py
softwares/load.py
softwares/load_test.py
softwares/module_test.py
softwares/promptware.py
softwares/software.py
softwaress-0.0.1.dist-info/LICENSE
softwaress-0.0.1.dist-info/METADATA
softwaress-0.0.1.dist-info/WHEEL
softwaress-0.0.1.dist-info/top_level.txt
softwaress-0.0.1.dist-info/RECORD
